numtoword_amiri/__init__.py
numtoword_amiri/en.py
numtoword_amiri/fa.py
numtoword_amiri-0.1.0.dist-info/LICENSE.txt
numtoword_amiri-0.1.0.dist-info/METADATA
numtoword_amiri-0.1.0.dist-info/WHEEL
numtoword_amiri-0.1.0.dist-info/top_level.txt
numtoword_amiri-0.1.0.dist-info/RECORD
