Metadata-Version: 2.1
Name: numtoword-amiri
Version: 0.1.0
Summary: convert number to word.
Author: mohammad javad amiri
Author-email: mohammadjavad.amiri.1997@gmail.com
Classifier: Programming Language :: Python :: 3
Classifier: License :: OSI Approved :: MIT License
Classifier: Operating System :: OS Independent
Requires-Python: >=3.6
License-File: LICENSE.txt
